pyvital/__init__.py
pyvital/__main__.py
pyvital/arr.py
pyvital/filters/UniMSNet.pth
pyvital/filters/__init__.py
pyvital/filters/abp_hpi.py
pyvital/filters/abp_ppv.py
pyvital/filters/ecg_annotator.py
pyvital/filters/ecg_beat_noise_detector.py
pyvital/filters/ecg_classifier.py
pyvital/filters/ecg_hrv.py
pyvital/filters/ecg_mtwa.py
pyvital/filters/ecg_qrs_detector.py
pyvital/filters/eeg_fft.py
pyvital/filters/model_beat.h5
pyvital/filters/model_dlapco_v1.pth
pyvital/filters/model_hpi_state_dict_v1.pth
pyvital/filters/model_rhythm.h5
pyvital/filters/nirs_cox.py
pyvital/filters/pkpd_3comp.py
pyvital/filters/pleth_dpop.py
pyvital/filters/pleth_ptt.py
pyvital/filters/pleth_pvi.py
pyvital/filters/pleth_spi.py
pyvital/filters/resp_compliance.py
pyvital/filters/sv_dlapco.py
pyvital-0.4.0.dist-info/licenses/LICENSE
pyvital-0.4.0.dist-info/METADATA
pyvital-0.4.0.dist-info/WHEEL
pyvital-0.4.0.dist-info/top_level.txt
pyvital-0.4.0.dist-info/RECORD
