Metadata-Version: 2.4
Name: pyvital
Version: 0.4.0
Summary: Python Libray for Biosignal Analysis
Author-email: VitalLab <vital@snu.ac.kr>
License-Expression: MIT
Requires-Python: >=3.8
License-File: LICENSE
Requires-Dist: numpy
Requires-Dist: scipy
Requires-Dist: sanic
Requires-Dist: PyWavelets
Requires-Dist: tensorflow>=2.6
Requires-Dist: keras
Requires-Dist: torch
Dynamic: license-file
